CodonU/__init__.py
CodonU/analyzer/__init__.py
CodonU/analyzer/aromaticity_comp.py
CodonU/analyzer/cai_comp.py
CodonU/analyzer/cbi_comp.py
CodonU/analyzer/enc_comp.py
CodonU/analyzer/generate_report.py
CodonU/analyzer/generate_report_summary.py
CodonU/analyzer/gravy_comp.py
CodonU/analyzer/internal_comp.py
CodonU/analyzer/rscu_comp.py
CodonU/analyzer/tRNA_comp.py
CodonU/correspondence_analysis/__init__.py
CodonU/correspondence_analysis/build_contingency_table_aa_count.py
CodonU/correspondence_analysis/build_contingency_table_codon_count.py
CodonU/correspondence_analysis/build_contingency_table_codon_rscu.py
CodonU/correspondence_analysis/ca_aa.py
CodonU/correspondence_analysis/ca_codon.py
CodonU/cua_errors/__init__.py
CodonU/cua_errors/bad_seq_err.py
CodonU/cua_errors/codon_table_exist_err.py
CodonU/cua_errors/codon_usage_err.py
CodonU/cua_errors/file_not_empty_err.py
CodonU/cua_errors/internal_stop_codon_err.py
CodonU/cua_errors/no_prot_err.py
CodonU/cua_errors/nucleotide_err.py
CodonU/cua_errors/ter_seq_err.py
CodonU/cua_errors/unsupported_db.py
CodonU/cua_errors/unsupported_type.py
CodonU/cua_warnings/__init__.py
CodonU/cua_warnings/api_warn.py
CodonU/cua_warnings/ca_component_warn.py
CodonU/cua_warnings/codon_usage_warns.py
CodonU/cua_warnings/email_warn.py
CodonU/cua_warnings/missing_codon_warn.py
CodonU/cua_warnings/no_codon_warn.py
CodonU/cua_warnings/no_syn_codon_warn.py
CodonU/extractor/__init__.py
CodonU/extractor/extract_cds.py
CodonU/extractor/extract_cds_lst.py
CodonU/extractor/extract_exome.py
CodonU/extractor/extract_prot.py
CodonU/extractor/internal_comp.py
CodonU/file_handler/__init__.py
CodonU/file_handler/get_gb.py
CodonU/file_handler/internal_comp.py
CodonU/file_handler/make_dir.py
CodonU/file_handler/read_file.py
CodonU/file_handler/set_entrez_param.py
CodonU/file_handler/write_exome_fasta.py
CodonU/file_handler/write_nucleotide_fasta.py
CodonU/file_handler/write_protein_fasta.py
CodonU/phylogenetic_analysis/__init__.py
CodonU-1.1.2.dist-info/LICENSE.md
CodonU-1.1.2.dist-info/METADATA
CodonU-1.1.2.dist-info/WHEEL
CodonU-1.1.2.dist-info/top_level.txt
CodonU-1.1.2.dist-info/RECORD
