Metadata-Version: 2.1
Name: CodonU
Version: 1.1.2
Summary: An integrated package for codon usage analysis
Home-page: https://github.com/SouradiptoC/codon_usage
Author: Souradipto Choudhuri
Author-email: Souradipto <sourochaudhuri@gmail.com>
License: MIT License
Project-URL: Bug Tracker, https://github.com/SouradiptoC/codon_usage/issues
Project-URL: Documentation, https://codonu.readthedocs.io/en/latest/?badge=latest
Project-URL: Source Code, https://github.com/SouradiptoC/codon_usage
Keywords: bioinformatics,bioinformatics-analysis,bioinformatics-tool,codon-usage,codon,codon-bias,genomic-analysis,genome,codonW,tAI
Classifier: Development Status :: 5 - Production/Stable
Classifier: Natural Language :: English
Classifier: Topic :: Scientific/Engineering :: Bio-Informatics
Classifier: License :: OSI Approved :: MIT License
Classifier: Programming Language :: Python :: 3
Classifier: Operating System :: Unix
Classifier: Operating System :: MacOS :: MacOS X
Classifier: Operating System :: Microsoft :: Windows
Classifier: Intended Audience :: Developers
Classifier: Intended Audience :: Education
Classifier: Intended Audience :: Healthcare Industry
Classifier: Intended Audience :: Science/Research
Requires-Python: >=3.11
License-File: LICENSE.md
Requires-Dist: biopython ~=1.79
Requires-Dist: numpy ~=1.24.2
Requires-Dist: pandas ~=2.1.1
Requires-Dist: matplotlib >=3.6.3
Requires-Dist: scipy ~=1.10.0
Requires-Dist: prince ~=0.12.1
Requires-Dist: gtAI ~=1.0.4
